zshot/__init__.py
zshot/config.py
zshot/pipeline_config.py
zshot/zshot.py
zshot/evaluation/__init__.py
zshot/evaluation/evaluator.py
zshot/evaluation/pipeline.py
zshot/evaluation/run_evaluation.py
zshot/evaluation/zshot_evaluate.py
zshot/evaluation/dataset/__init__.py
zshot/evaluation/dataset/dataset.py
zshot/evaluation/dataset/fewrel/__init__.py
zshot/evaluation/dataset/fewrel/fewrel.py
zshot/evaluation/dataset/med_mentions/__init__.py
zshot/evaluation/dataset/med_mentions/entities.py
zshot/evaluation/dataset/med_mentions/med_mentions.py
zshot/evaluation/dataset/med_mentions/utils.py
zshot/evaluation/dataset/ontonotes/__init__.py
zshot/evaluation/dataset/ontonotes/entities.py
zshot/evaluation/dataset/ontonotes/onto_notes.py
zshot/evaluation/metrics/__init__.py
zshot/evaluation/metrics/rel_eval.py
zshot/evaluation/metrics/_seqeval/__init__.py
zshot/evaluation/metrics/_seqeval/_seqeval.py
zshot/knowledge_extractor/__init__.py
zshot/knowledge_extractor/knowledge_extractor.py
zshot/knowledge_extractor/knowgl/__init__.py
zshot/knowledge_extractor/knowgl/knowledge_extractor_knowgl.py
zshot/knowledge_extractor/knowgl/utils.py
zshot/linker/__init__.py
zshot/linker/linker.py
zshot/linker/linker_blink.py
zshot/linker/linker_gliner.py
zshot/linker/linker_smxm.py
zshot/linker/linker_tars.py
zshot/linker/linker_ensemble/__init__.py
zshot/linker/linker_ensemble/linker_ensemble.py
zshot/linker/linker_ensemble/utils.py
zshot/linker/linker_regen/__init__.py
zshot/linker/linker_regen/linker_regen.py
zshot/linker/linker_regen/trie.py
zshot/linker/linker_regen/utils.py
zshot/mentions_extractor/__init__.py
zshot/mentions_extractor/mentions_extractor.py
zshot/mentions_extractor/mentions_extractor_flair.py
zshot/mentions_extractor/mentions_extractor_gliner.py
zshot/mentions_extractor/mentions_extractor_smxm.py
zshot/mentions_extractor/mentions_extractor_spacy.py
zshot/mentions_extractor/mentions_extractor_tars.py
zshot/mentions_extractor/utils/ExtractorType.py
zshot-0.0.10.dist-info/licenses/LICENSE
zshot-0.0.10.dist-info/METADATA
zshot-0.0.10.dist-info/WHEEL
zshot-0.0.10.dist-info/top_level.txt
zshot-0.0.10.dist-info/RECORD
