Metadata-Version: 2.4
Name: zshot
Version: 0.0.10
Summary: Zero and Few shot named entity recognition
Home-page: https://ibm.github.io/zshot
Author: IBM Research
Author-email: 
License: MIT
Keywords: NER Zero-Shot Few-Shot
License-File: LICENSE
Requires-Dist: spacy>=3.4.1
Requires-Dist: requests>=2.28
Requires-Dist: tqdm>=4.62.3
Requires-Dist: setuptools>=65.5.1
Requires-Dist: prettytable>=3.4
Requires-Dist: torch>=1
Requires-Dist: transformers>=4.20
Requires-Dist: datasets>=2.9.1
Requires-Dist: evaluate>=0.3.0
Requires-Dist: seqeval>=1.2.2
Dynamic: author
Dynamic: description
Dynamic: description-content-type
Dynamic: home-page
Dynamic: keywords
Dynamic: license
Dynamic: license-file
Dynamic: requires-dist
Dynamic: summary
